.DS_Store
rapo/.DS_Store
rapo/__init__.py
rapo/config.py
rapo/database.py
rapo/logger.py
rapo/reader.py
rapo/utils.py
rapo/algorithms/rec/db/create_comb_table.sql
rapo/algorithms/rec/db/create_dup_a_table.sql
rapo/algorithms/rec/db/create_dup_b_table.sql
rapo/algorithms/rec/db/create_dup_table.sql
rapo/algorithms/rec/db/create_nf_a_table.sql
rapo/algorithms/rec/db/create_nf_b_table.sql
rapo/algorithms/rec/db/save_err_a_table.sql
rapo/algorithms/rec/db/save_err_b_table.sql
rapo/algorithms/rec/db/save_rec_a_table.sql
rapo/algorithms/rec/db/save_rec_b_table.sql
rapo/algorithms/rec/db/exps/discrepancy_desc.sql
rapo/algorithms/rec/db/exps/discrepancy_field.sql
rapo/algorithms/rec/db/exps/discrepancy_filter.sql
rapo/algorithms/rec/db/exps/discrepancy_formula.sql
rapo/algorithms/rec/db/exps/discrepancy_percentage.sql
rapo/algorithms/rec/db/exps/discrepancy_rule.sql
rapo/algorithms/reconciliation/create_comb_table.sql
rapo/algorithms/reconciliation/create_dup_a_table.sql
rapo/algorithms/reconciliation/create_dup_b_table.sql
rapo/algorithms/reconciliation/create_dup_table.sql
rapo/algorithms/reconciliation/create_nf_a_table.sql
rapo/algorithms/reconciliation/create_nf_b_table.sql
rapo/algorithms/reconciliation/s01_correlate.sql
rapo/algorithms/reconciliation/s02_organize_a.sql
rapo/algorithms/reconciliation/s02_organize_b.sql
rapo/algorithms/reconciliation/s03_prepare_duplicates_a.sql
rapo/algorithms/reconciliation/s03_prepare_duplicates_b.sql
rapo/algorithms/reconciliation/s04_process_duplicates.sql
rapo/algorithms/reconciliation/s05_match_duplicates.sql
rapo/algorithms/reconciliation/s05_match_duplicates_a.sql
rapo/algorithms/reconciliation/s05_match_duplicates_b.sql
rapo/algorithms/reconciliation/s06_prepare_conflicts.sql
rapo/algorithms/reconciliation/s07_match_conflicts.sql
rapo/algorithms/reconciliation/s08_save_error_a.sql
rapo/algorithms/reconciliation/s08_save_error_b.sql
rapo/algorithms/reconciliation/s09_save_stage_a.sql
rapo-0.6.13.dist-info/LICENSE
rapo-0.6.13.dist-info/METADATA
rapo-0.6.13.dist-info/WHEEL
rapo-0.6.13.dist-info/top_level.txt
rapo-0.6.13.dist-info/RECORD
