Metadata-Version: 2.1
Name: rapo
Version: 0.6.13
Summary: Python Revenue Assurance Process Optimizer.
Home-page: https://github.com/t3eHawk/rapo
Author: Timur Faradzhov
Author-email: timurfaradzhov@gmail.com
License: MIT
Classifier: Programming Language :: Python :: 3.7
Classifier: Programming Language :: Python :: 3.11
Classifier: License :: OSI Approved :: MIT License
Classifier: Operating System :: OS Independent
Requires-Python: >=3.7
License-File: LICENSE
Requires-Dist: pepperoni (==0.2.1)
Requires-Dist: psutil (==5.9.5)
Requires-Dist: sqlparse (==0.4.4)
Requires-Dist: flask (==2.2.5)
Requires-Dist: flask-httpauth (==4.8.0)
Requires-Dist: waitress (==2.1.2)
Requires-Dist: SQLAlchemy (==1.4.46)
Requires-Dist: cx-Oracle (==8.3.0)
